{
    "Isan’andininy:": [
        "Isan’andininy:\n",
        "Laza sy haja ho Anao (Ho Anao) \n",
        "Ry Mpamonjy sy Mpanavotra ô! \n",
        "Indro foana re ny fasanao \n",
        "Ry Mpanjaka Tompon’aina ô! \n",
        "Raiso re (Raiso re) Tomponay (Tomponay) \n",
        "Dera ho mandrakizay\n"
    ],
    "1.": [
        "1.\n",
        "Jeso natsangana \n",
        "Ka hobio re \n",
        "Resy ny fasana \n",
        "Afaka ê!\n"
    ],
    "2.": [
        "2.\n",
        "Jeso natsangana \n",
        "Toky ho anao \n",
        "‘Zay anovozana \n",
        "Hery vaovao\n"
    ],
    "3.": [
        "3.\n",
        "Jeso Mpanjaka izao \n",
        "Miaraka amin-dRay \n",
        "Te hampanjaka anao \n",
        "Mandrakizay"
    ],
    "ord": [
        
        "1.","Isan’andininy:",
        "2.","Isan’andininy:",
        "3.","Isan’andininy:"
    ]
}