{
    "NY FOKO NO MIFALY": [
        "NY FOKO NO MIFALY\n"
    ],
    "1": [
        "1\n",
        "Ny foko no mifaly fa navotanao\n",
        "Voaheloka ho very fa nafâhanao\n",
        "Nomenao koa honenako ny\n",
        "lanitra\n",
        "Fonenan’ny voavotra\n"
    ],
    "2": [
        "2\n",
        "Kanefa izaho dia tsy maintsy\n",
        "miomana\n",
        "Raha mbola manodidina ny olona\n",
        "Ny haizin’ota izay efa nilaozako Dia\n",
        "tsy mba hiverenako\n"
    ],
    "3": [
        "3\n",
        "Adidiko mandray farango fitana Harato\n",
        "izay azoko ho entina Hamory olona ho\n",
        "any an-dàiitra Ny tenin’Andriamanitra\n"
    ],
    "Isan'andininy": [
        "Isan'andininy\n",
        "Tsy ny ety no ifaliako, Fa zava-poana\n",
        "raha ny etÿ Jesosy no andrasanao ry\n",
        "foko\n",
        "Ary andanitra ary"
    ],
    "ord": [
        "1",
        "2",
        "3",
        "Isan'andininy"
    ]
}